pyranch/__init__.py
pyranch/cattle.py
pyranch/common.py
pyranch/exceptions.py
pyranch/hosts.py
pyranch/services.py
pyranch/stacks.py
pyranch/storage_drivers.py
pyranch/subscribe.py
pyranch/volumes.py
pyranch-0.0.6.dist-info/METADATA
pyranch-0.0.6.dist-info/WHEEL
pyranch-0.0.6.dist-info/top_level.txt
pyranch-0.0.6.dist-info/RECORD
