Metadata-Version: 2.1
Name: pyranch
Version: 0.0.6
Summary: Rancher API SDK
Home-page: https://github.com/fedetorre/pyranch
Author: Federico Torresan
Author-email: federico.torresan@quentral.com
License: LGPLv3
Platform: UNKNOWN
Classifier: Development Status :: 1 - Planning
Classifier: Intended Audience :: Developers
Classifier: Operating System :: OS Independent
Classifier: Topic :: Software Development :: Libraries
Classifier: Programming Language :: Python
Classifier: Programming Language :: Python :: 3
Classifier: Programming Language :: Python :: 3.6
Classifier: Programming Language :: Python :: 3.7
Classifier: Programming Language :: Python :: 3.8
Requires-Dist: requests (==2.26.0)
Requires-Dist: websocket-client (==0.45.0)
